setup.py
dist/dm.zodb.repair-1.0.tar.gz
dm/__init__.py
dm.zodbpatches.commit_savepoint.egg-info/PKG-INFO
dm.zodbpatches.commit_savepoint.egg-info/SOURCES.txt
dm.zodbpatches.commit_savepoint.egg-info/dependency_links.txt
dm.zodbpatches.commit_savepoint.egg-info/namespace_packages.txt
dm.zodbpatches.commit_savepoint.egg-info/not-zip-safe
dm.zodbpatches.commit_savepoint.egg-info/requires.txt
dm.zodbpatches.commit_savepoint.egg-info/top_level.txt
dm/zodbpatches/__init__.py
dm/zodbpatches/commit_savepoint/README.txt
dm/zodbpatches/commit_savepoint/VERSION.txt
dm/zodbpatches/commit_savepoint/__init__.py
dm/zodbpatches/commit_savepoint/tests.py