Metadata-Version: 1.1
Name: dm.zodbpatches.commit-savepoint
Version: 1.0.1
Summary: Patch ZODB to work around https://github.com/zopefoundation/ZODB3/issues/2
Home-page: http://pypi.python.org/pypi/dm.zodbpatches.commit_savepoint
Author: Dieter Maurer
Author-email: dieter@handshake.de
License: ZPL
Keywords: ZODB patch
Platform: UNKNOWN
Classifier: Development Status :: 5 - Production/Stable
Classifier: Intended Audience :: Developers
Classifier: License :: OSI Approved :: Zope Public License
Classifier: Framework :: ZODB
Classifier: Operating System :: OS Independent
Classifier: Programming Language :: Python
Classifier: Topic :: Utilities
